aiterm/__init__.py
aiterm/claude/__init__.py
aiterm/claude/settings.py
aiterm/claude/.claude/settings.local.json
aiterm/cli/__init__.py
aiterm/cli/agents.py
aiterm/cli/commands.py
aiterm/cli/config.py
aiterm/cli/craft.py
aiterm/cli/docs.py
aiterm/cli/feature.py
aiterm/cli/gemini.py
aiterm/cli/ghostty.py
aiterm/cli/hooks.py
aiterm/cli/ide.py
aiterm/cli/learn.py
aiterm/cli/main.py
aiterm/cli/mcp.py
aiterm/cli/memory.py
aiterm/cli/opencode.py
aiterm/cli/plugins.py
aiterm/cli/release.py
aiterm/cli/sessions.py
aiterm/cli/statusbar.py
aiterm/cli/statusline.py
aiterm/cli/styles.py
aiterm/cli/terminals.py
aiterm/cli/workflows.py
aiterm/commands/__init__.py
aiterm/commands/library.py
aiterm/config/__init__.py
aiterm/config/paths.py
aiterm/context/__init__.py
aiterm/context/detector.py
aiterm/docs/__init__.py
aiterm/docs/validator.py
aiterm/hooks/__init__.py
aiterm/hooks/manager.py
aiterm/mcp/__init__.py
aiterm/mcp/manager.py
aiterm/opencode/__init__.py
aiterm/opencode/config.py
aiterm/statusline/USAGE-SETUP.md
aiterm/statusline/USAGE-TRACKING-README.md
aiterm/statusline/__init__.py
aiterm/statusline/agents.py
aiterm/statusline/config.py
aiterm/statusline/hooks.py
aiterm/statusline/interactive.py
aiterm/statusline/renderer.py
aiterm/statusline/segments.py
aiterm/statusline/themes.py
aiterm/statusline/usage.py
aiterm/terminal/__init__.py
aiterm/terminal/ghostty.py
aiterm/terminal/iterm2.py
aiterm/utils/__init__.py
aiterm/utils/tutorial.py
aiterm_dev-0.7.2.dist-info/METADATA
aiterm_dev-0.7.2.dist-info/WHEEL
aiterm_dev-0.7.2.dist-info/entry_points.txt
aiterm_dev-0.7.2.dist-info/RECORD
